{
    "seed_urls": [
        "https://www.myslo.ru/news",
        "https://www.myslo.ru/news/main/fresh/2",
        "https://www.myslo.ru/news/main/fresh/3",
        "https://www.myslo.ru/news/main/fresh/4",
        "https://www.myslo.ru/news/main/fresh/5",
        "https://www.myslo.ru/news/main/fresh/6",
        "https://www.myslo.ru/news/main/fresh/7",
        "https://www.myslo.ru/news/main/fresh/8",
        "https://www.myslo.ru/news/main/fresh/9",
        "https://www.myslo.ru/news/main/fresh/10",
        "https://www.myslo.ru/news/main/fresh/11",
        "https://www.myslo.ru/news/main/fresh/12",
        "https://www.myslo.ru/news/main/fresh/13",
        "https://www.myslo.ru/news/main/fresh/14",
        "https://www.myslo.ru/news/main/fresh/15"
    ],
    "headers": {"cookie": "stg_traffic_source_priority=4; stg_externalReferrer=https://www.google.com/; stg_last_interaction=Mon%2C%2008%20Apr%202024%2009:20:56%20GMT; stg_returning_visitor=Mon%2C%2008%20Apr%202024%2009:20:56%20GMT",
    "accept-language":"ru-RU,ru;q=0.9",
    "accept": "text/html,application/xhtml+xml,application/xml;q=0.9,image/avif,image/webp,image/apng,*/*;q=0.8,application/signed-exchange;v=b3;q=0.7",
    "user-agent": "Mozilla/5.0 (Windows NT 10.0; Win64; x64) AppleWebKit/537.36 (KHTML, like Gecko) Chrome/123.0.0.0 Safari/537.36"},
    "total_articles_to_find_and_parse": 5,
    "encoding": "utf-8",
    "timeout": 30,
    "should_verify_certificate": true,
    "headless_mode": true
}
